django_factory_boy/__init__.py
django_factory_boy/auth.py
django_factory_boy/models.py
django_factory_boy/sites.py
django_factory_boy/tests.py
django_factory_boy-1.0.0.dist-info/DESCRIPTION.rst
django_factory_boy-1.0.0.dist-info/METADATA
django_factory_boy-1.0.0.dist-info/RECORD
django_factory_boy-1.0.0.dist-info/WHEEL
django_factory_boy-1.0.0.dist-info/metadata.json
django_factory_boy-1.0.0.dist-info/top_level.txt
