Metadata-Version: 1.1
Name: django-factory-boy
Version: 1.0.0
Summary: Uses factory_boy to supply test data factory classes for all stock Django models.
Home-page: http://github.com/rbarrois/django-factory_boy
Author: Raphaël Barrois
Author-email: raphael.barrois+fboy@polytechnique.org
License: BSD
Keywords: factory_boy,django,fixtures
Platform: UNKNOWN
Classifier: Development Status :: 5 - Production/Stable
Classifier: Intended Audience :: Developers
Classifier: Framework :: Django
Classifier: License :: OSI Approved :: BSD License
Classifier: Operating System :: OS Independent
Classifier: Programming Language :: Python
Classifier: Programming Language :: Python :: 2
Classifier: Programming Language :: Python :: 2.6
Classifier: Programming Language :: Python :: 2.7
Classifier: Programming Language :: Python :: 3
Classifier: Programming Language :: Python :: 3.2
Classifier: Programming Language :: Python :: 3.3
Classifier: Programming Language :: Python :: 3.4
Classifier: Topic :: Software Development :: Testing
Classifier: Topic :: Software Development :: Libraries :: Python Modules
